sample_ds_project/__init__.py
sample_ds_project/components/__init__.py
sample_ds_project/config/__init__.py
sample_ds_project/constants/__init__.py
sample_ds_project/entity/__init__.py
sample_ds_project/exception/__init__.py
sample_ds_project/foo.py
sample_ds_project/logging/__init__.py
sample_ds_project/main.py
sample_ds_project/pipeline/__init__.py
sample_ds_project/pipeline/prediction.py
sample_ds_project/pipeline/stage_01_data_ingestion.py
sample_ds_project/pipeline/stage_02_data_validation.py
sample_ds_project/pipeline/stage_03_data_transformation.py
sample_ds_project/pipeline/stage_04_model_trainer.py
sample_ds_project/pipeline/stage_05_model_evaluation.py
sample_ds_project/routes/__init__.py
sample_ds_project/routes/router.py
sample_ds_project/utils/__init__.py
sample_ds_project/utils/common.py
sample_ds_project-0.0.8.dist-info/LICENSE
sample_ds_project-0.0.8.dist-info/METADATA
sample_ds_project-0.0.8.dist-info/WHEEL
sample_ds_project-0.0.8.dist-info/entry_points.txt
sample_ds_project-0.0.8.dist-info/RECORD
