Metadata-Version: 2.1
Name: sample_ds_project
Version: 0.0.8
Summary: A Sample Project for Data Science experiments
Home-page: https://github.com/DeepakPant93/sample-ds-project
Author: Deepak Pant
Author-email: deepak.93p@gmail.com
Requires-Python: >=3.11,<4.0
Classifier: Programming Language :: Python :: 3
Classifier: Programming Language :: Python :: 3.11
Classifier: Programming Language :: Python :: 3.12
Requires-Dist: ensure (>=1.0.4,<2.0.0)
Requires-Dist: fastapi (>=0.100.0,<0.101.0)
Requires-Dist: fastapi-health (>=0.4.0,<0.5.0)
Requires-Dist: joblib (>=1.3.2,<2.0.0)
Requires-Dist: python-box (>=7.2.0,<8.0.0)
Requires-Dist: pyyaml (>=6.0.2,<7.0.0)
Requires-Dist: uvicorn (>=0.23.0,<0.24.0)
Project-URL: Documentation, https://DeepakPant93.github.io/sample-ds-project/
Project-URL: Repository, https://github.com/DeepakPant93/sample-ds-project
